price_tracker/__init__.py
price_tracker/__main__.py
price_tracker/commands.py
price_tracker/helpers.py
price_tracker/price_tracker.py
price_tracker/scraper.py
price_tracker-0.2.dist-info/LICENSE
price_tracker-0.2.dist-info/METADATA
price_tracker-0.2.dist-info/WHEEL
price_tracker-0.2.dist-info/entry_points.txt
price_tracker-0.2.dist-info/top_level.txt
price_tracker-0.2.dist-info/RECORD
