Metadata-Version: 2.1
Name: price-tracker
Version: 0.2
Summary: a python application to track prices on some online shopping applications
Home-page: https://github.com/Evasionn/price-tracker/
Author: Melihşah Akın
Author-email: melihsahakin@gmail.com
License: gpl13
Project-URL: Documentation, https://pyscaffold.org/
Platform: any
Classifier: Development Status :: 4 - Beta
Classifier: Programming Language :: Python
Requires-Dist: beautifulsoup4
Requires-Dist: requests
Provides-Extra: testing
Requires-Dist: pytest ; extra == 'testing'
Requires-Dist: pytest-cov ; extra == 'testing'
